[
  {
    "type": "post",
    "url": "/article",
    "title": "Article",
    "version": "0.3.0",
    "name": "PostArticle",
    "group": "Getter",
    "permission": [
      {
        "name": "none"
      }
    ],
    "description": "<p>文章（获取文章的详细内容）</p>",
    "parameter": {
      "fields": {
        "Parameter": [
          {
            "group": "Parameter",
            "type": "String",
            "optional": false,
            "field": "id",
            "description": "<p>文章的id.</p>"
          }
        ]
      }
    },
    "success": {
      "fields": {
        "Success 200": [
          {
            "group": "Success 200",
            "type": "Number",
            "optional": false,
            "field": "id",
            "description": "<p>The new Users-ID.</p>"
          }
        ]
      }
    },
    "filename": "example/example.js",
    "groupTitle": "Getter",
    "sampleRequest": [
      {
        "url": "https://devonhello.com/chihu_v3/article"
      }
    ],
    "error": {
      "fields": {
        "Error 4xx": [
          {
            "group": "Error 4xx",
            "optional": false,
            "field": "NoAccessRight",
            "description": "<p>Only authenticated Admins can access the data.</p>"
          },
          {
            "group": "Error 4xx",
            "optional": false,
            "field": "UserNameTooShort",
            "description": "<p>Minimum of 5 characters required.</p>"
          }
        ]
      },
      "examples": [
        {
          "title": "Response (example):",
          "content": "HTTP/1.1 400 Bad Request\n{\n  \"error\": \"UserNameTooShort\"\n}",
          "type": "json"
        }
      ]
    }
  },
  {
    "type": "post",
    "url": "/article_list",
    "title": "ArticleList",
    "version": "0.3.0",
    "name": "PostArticleList",
    "group": "Getter",
    "permission": [
      {
        "name": "none"
      }
    ],
    "description": "<p>文章列表</p>",
    "parameter": {
      "fields": {
        "Parameter": [
          {
            "group": "Parameter",
            "type": "Number",
            "optional": false,
            "field": "skip",
            "description": "<p>跳过指定数量.</p>"
          },
          {
            "group": "Parameter",
            "type": "Number",
            "optional": false,
            "field": "limit",
            "description": "<p>读取的记录条数.</p>"
          }
        ]
      }
    },
    "success": {
      "fields": {
        "Success 200": [
          {
            "group": "Success 200",
            "type": "Number",
            "optional": false,
            "field": "id",
            "description": "<p>The new Users-ID.</p>"
          }
        ]
      }
    },
    "filename": "example/example.js",
    "groupTitle": "Getter",
    "sampleRequest": [
      {
        "url": "https://devonhello.com/chihu_v3/article_list"
      }
    ],
    "error": {
      "fields": {
        "Error 4xx": [
          {
            "group": "Error 4xx",
            "optional": false,
            "field": "NoAccessRight",
            "description": "<p>Only authenticated Admins can access the data.</p>"
          },
          {
            "group": "Error 4xx",
            "optional": false,
            "field": "UserNameTooShort",
            "description": "<p>Minimum of 5 characters required.</p>"
          }
        ]
      },
      "examples": [
        {
          "title": "Response (example):",
          "content": "HTTP/1.1 400 Bad Request\n{\n  \"error\": \"UserNameTooShort\"\n}",
          "type": "json"
        }
      ]
    }
  },
  {
    "type": "post",
    "url": "/focus_question",
    "title": "FocusQuestion",
    "version": "0.3.0",
    "name": "PostFocusQuestion",
    "group": "Getter",
    "permission": [
      {
        "name": "none"
      }
    ],
    "description": "<p>我关注的提问</p>",
    "parameter": {
      "fields": {
        "Parameter": [
          {
            "group": "Parameter",
            "type": "String",
            "optional": false,
            "field": "id",
            "description": "<p>用户id.</p>"
          },
          {
            "group": "Parameter",
            "type": "Number",
            "optional": false,
            "field": "skip",
            "description": "<p>跳过指定数量.</p>"
          },
          {
            "group": "Parameter",
            "type": "Number",
            "optional": false,
            "field": "limit",
            "description": "<p>读取的记录条数.</p>"
          }
        ]
      }
    },
    "success": {
      "fields": {
        "Success 200": [
          {
            "group": "Success 200",
            "type": "Number",
            "optional": false,
            "field": "id",
            "description": "<p>The new Users-ID.</p>"
          }
        ]
      }
    },
    "filename": "example/example.js",
    "groupTitle": "Getter",
    "sampleRequest": [
      {
        "url": "https://devonhello.com/chihu_v3/focus_question"
      }
    ],
    "error": {
      "fields": {
        "Error 4xx": [
          {
            "group": "Error 4xx",
            "optional": false,
            "field": "NoAccessRight",
            "description": "<p>Only authenticated Admins can access the data.</p>"
          },
          {
            "group": "Error 4xx",
            "optional": false,
            "field": "UserNameTooShort",
            "description": "<p>Minimum of 5 characters required.</p>"
          }
        ]
      },
      "examples": [
        {
          "title": "Response (example):",
          "content": "HTTP/1.1 400 Bad Request\n{\n  \"error\": \"UserNameTooShort\"\n}",
          "type": "json"
        }
      ]
    }
  },
  {
    "type": "post",
    "url": "/follower",
    "title": "Follower",
    "version": "0.3.0",
    "name": "PostFollower",
    "group": "Getter",
    "permission": [
      {
        "name": "none"
      }
    ],
    "description": "<p>获取用户的粉丝</p>",
    "parameter": {
      "fields": {
        "Parameter": [
          {
            "group": "Parameter",
            "type": "String",
            "optional": false,
            "field": "id",
            "description": "<p>用户id.</p>"
          }
        ]
      }
    },
    "success": {
      "fields": {
        "Success 200": [
          {
            "group": "Success 200",
            "type": "Number",
            "optional": false,
            "field": "id",
            "description": "<p>The new Users-ID.</p>"
          }
        ]
      }
    },
    "filename": "example/example.js",
    "groupTitle": "Getter",
    "sampleRequest": [
      {
        "url": "https://devonhello.com/chihu_v3/follower"
      }
    ],
    "error": {
      "fields": {
        "Error 4xx": [
          {
            "group": "Error 4xx",
            "optional": false,
            "field": "NoAccessRight",
            "description": "<p>Only authenticated Admins can access the data.</p>"
          },
          {
            "group": "Error 4xx",
            "optional": false,
            "field": "UserNameTooShort",
            "description": "<p>Minimum of 5 characters required.</p>"
          }
        ]
      },
      "examples": [
        {
          "title": "Response (example):",
          "content": "HTTP/1.1 400 Bad Request\n{\n  \"error\": \"UserNameTooShort\"\n}",
          "type": "json"
        }
      ]
    }
  },
  {
    "type": "post",
    "url": "/following",
    "title": "Following",
    "version": "0.3.0",
    "name": "PostFollowing",
    "group": "Getter",
    "permission": [
      {
        "name": "none"
      }
    ],
    "description": "<p>获取用户关注的人</p>",
    "parameter": {
      "fields": {
        "Parameter": [
          {
            "group": "Parameter",
            "type": "String",
            "optional": false,
            "field": "id",
            "description": "<p>用户id.</p>"
          }
        ]
      }
    },
    "success": {
      "fields": {
        "Success 200": [
          {
            "group": "Success 200",
            "type": "Number",
            "optional": false,
            "field": "id",
            "description": "<p>The new Users-ID.</p>"
          }
        ]
      }
    },
    "filename": "example/example.js",
    "groupTitle": "Getter",
    "sampleRequest": [
      {
        "url": "https://devonhello.com/chihu_v3/following"
      }
    ],
    "error": {
      "fields": {
        "Error 4xx": [
          {
            "group": "Error 4xx",
            "optional": false,
            "field": "NoAccessRight",
            "description": "<p>Only authenticated Admins can access the data.</p>"
          },
          {
            "group": "Error 4xx",
            "optional": false,
            "field": "UserNameTooShort",
            "description": "<p>Minimum of 5 characters required.</p>"
          }
        ]
      },
      "examples": [
        {
          "title": "Response (example):",
          "content": "HTTP/1.1 400 Bad Request\n{\n  \"error\": \"UserNameTooShort\"\n}",
          "type": "json"
        }
      ]
    }
  },
  {
    "type": "post",
    "url": "/iclass",
    "title": "Iclass",
    "version": "0.3.0",
    "name": "PostIclass",
    "group": "Getter",
    "permission": [
      {
        "name": "none"
      }
    ],
    "description": "<p>菜谱分类</p>",
    "parameter": {
      "fields": {
        "Parameter": [
          {
            "group": "Parameter",
            "type": "String",
            "optional": false,
            "field": "id",
            "description": "<p>分类的id.</p>"
          }
        ]
      }
    },
    "success": {
      "fields": {
        "Success 200": [
          {
            "group": "Success 200",
            "type": "Number",
            "optional": false,
            "field": "id",
            "description": "<p>The new Users-ID.</p>"
          }
        ]
      }
    },
    "filename": "example/example.js",
    "groupTitle": "Getter",
    "sampleRequest": [
      {
        "url": "https://devonhello.com/chihu_v3/iclass"
      }
    ],
    "error": {
      "fields": {
        "Error 4xx": [
          {
            "group": "Error 4xx",
            "optional": false,
            "field": "NoAccessRight",
            "description": "<p>Only authenticated Admins can access the data.</p>"
          },
          {
            "group": "Error 4xx",
            "optional": false,
            "field": "UserNameTooShort",
            "description": "<p>Minimum of 5 characters required.</p>"
          }
        ]
      },
      "examples": [
        {
          "title": "Response (example):",
          "content": "HTTP/1.1 400 Bad Request\n{\n  \"error\": \"UserNameTooShort\"\n}",
          "type": "json"
        }
      ]
    }
  },
  {
    "type": "post",
    "url": "/like",
    "title": "Like",
    "version": "0.3.0",
    "name": "PostLike",
    "group": "Getter",
    "permission": [
      {
        "name": "none"
      }
    ],
    "description": "<p>我点赞过的分享</p>",
    "parameter": {
      "fields": {
        "Parameter": [
          {
            "group": "Parameter",
            "type": "String",
            "optional": false,
            "field": "id",
            "description": "<p>用户id.</p>"
          },
          {
            "group": "Parameter",
            "type": "Number",
            "optional": false,
            "field": "skip",
            "description": "<p>跳过指定数量.</p>"
          },
          {
            "group": "Parameter",
            "type": "Number",
            "optional": false,
            "field": "limit",
            "description": "<p>读取的记录条数.</p>"
          }
        ]
      }
    },
    "success": {
      "fields": {
        "Success 200": [
          {
            "group": "Success 200",
            "type": "Number",
            "optional": false,
            "field": "id",
            "description": "<p>The new Users-ID.</p>"
          }
        ]
      }
    },
    "filename": "example/example.js",
    "groupTitle": "Getter",
    "sampleRequest": [
      {
        "url": "https://devonhello.com/chihu_v3/like"
      }
    ],
    "error": {
      "fields": {
        "Error 4xx": [
          {
            "group": "Error 4xx",
            "optional": false,
            "field": "NoAccessRight",
            "description": "<p>Only authenticated Admins can access the data.</p>"
          },
          {
            "group": "Error 4xx",
            "optional": false,
            "field": "UserNameTooShort",
            "description": "<p>Minimum of 5 characters required.</p>"
          }
        ]
      },
      "examples": [
        {
          "title": "Response (example):",
          "content": "HTTP/1.1 400 Bad Request\n{\n  \"error\": \"UserNameTooShort\"\n}",
          "type": "json"
        }
      ]
    }
  },
  {
    "type": "post",
    "url": "/login",
    "title": "Login",
    "version": "0.3.0",
    "name": "PostLogin",
    "group": "Getter",
    "permission": [
      {
        "name": "none"
      }
    ],
    "description": "<p>搜索</p>",
    "parameter": {
      "fields": {
        "Parameter": [
          {
            "group": "Parameter",
            "type": "String",
            "optional": false,
            "field": "name",
            "description": "<p>账号.</p>"
          },
          {
            "group": "Parameter",
            "type": "String",
            "optional": false,
            "field": "password",
            "description": "<p>密码.</p>"
          }
        ]
      }
    },
    "success": {
      "fields": {
        "Success 200": [
          {
            "group": "Success 200",
            "type": "Number",
            "optional": false,
            "field": "id",
            "description": "<p>The new Users-ID.</p>"
          }
        ]
      }
    },
    "filename": "example/example.js",
    "groupTitle": "Getter",
    "sampleRequest": [
      {
        "url": "https://devonhello.com/chihu_v3/login"
      }
    ],
    "error": {
      "fields": {
        "Error 4xx": [
          {
            "group": "Error 4xx",
            "optional": false,
            "field": "NoAccessRight",
            "description": "<p>Only authenticated Admins can access the data.</p>"
          },
          {
            "group": "Error 4xx",
            "optional": false,
            "field": "UserNameTooShort",
            "description": "<p>Minimum of 5 characters required.</p>"
          }
        ]
      },
      "examples": [
        {
          "title": "Response (example):",
          "content": "HTTP/1.1 400 Bad Request\n{\n  \"error\": \"UserNameTooShort\"\n}",
          "type": "json"
        }
      ]
    }
  },
  {
    "type": "post",
    "url": "/my_article",
    "title": "MyArticle",
    "version": "0.3.0",
    "name": "PostMyArticle",
    "group": "Getter",
    "permission": [
      {
        "name": "none"
      }
    ],
    "description": "<p>我发布的文章</p>",
    "parameter": {
      "fields": {
        "Parameter": [
          {
            "group": "Parameter",
            "type": "String",
            "optional": false,
            "field": "id",
            "description": "<p>用户id.</p>"
          },
          {
            "group": "Parameter",
            "type": "Number",
            "optional": false,
            "field": "skip",
            "description": "<p>跳过指定数量.</p>"
          },
          {
            "group": "Parameter",
            "type": "Number",
            "optional": false,
            "field": "limit",
            "description": "<p>读取的记录条数.</p>"
          }
        ]
      }
    },
    "success": {
      "fields": {
        "Success 200": [
          {
            "group": "Success 200",
            "type": "Number",
            "optional": false,
            "field": "id",
            "description": "<p>The new Users-ID.</p>"
          }
        ]
      }
    },
    "filename": "example/example.js",
    "groupTitle": "Getter",
    "sampleRequest": [
      {
        "url": "https://devonhello.com/chihu_v3/my_article"
      }
    ],
    "error": {
      "fields": {
        "Error 4xx": [
          {
            "group": "Error 4xx",
            "optional": false,
            "field": "NoAccessRight",
            "description": "<p>Only authenticated Admins can access the data.</p>"
          },
          {
            "group": "Error 4xx",
            "optional": false,
            "field": "UserNameTooShort",
            "description": "<p>Minimum of 5 characters required.</p>"
          }
        ]
      },
      "examples": [
        {
          "title": "Response (example):",
          "content": "HTTP/1.1 400 Bad Request\n{\n  \"error\": \"UserNameTooShort\"\n}",
          "type": "json"
        }
      ]
    }
  },
  {
    "type": "post",
    "url": "/my_share",
    "title": "MyShare",
    "version": "0.3.0",
    "name": "PostMyShare",
    "group": "Getter",
    "permission": [
      {
        "name": "none"
      }
    ],
    "description": "<p>我发布的分享</p>",
    "parameter": {
      "fields": {
        "Parameter": [
          {
            "group": "Parameter",
            "type": "String",
            "optional": false,
            "field": "id",
            "description": "<p>用户id.</p>"
          },
          {
            "group": "Parameter",
            "type": "Number",
            "optional": false,
            "field": "skip",
            "description": "<p>跳过指定数量.</p>"
          },
          {
            "group": "Parameter",
            "type": "Number",
            "optional": false,
            "field": "limit",
            "description": "<p>读取的记录条数.</p>"
          }
        ]
      }
    },
    "success": {
      "fields": {
        "Success 200": [
          {
            "group": "Success 200",
            "type": "Number",
            "optional": false,
            "field": "id",
            "description": "<p>The new Users-ID.</p>"
          }
        ]
      }
    },
    "filename": "example/example.js",
    "groupTitle": "Getter",
    "sampleRequest": [
      {
        "url": "https://devonhello.com/chihu_v3/my_share"
      }
    ],
    "error": {
      "fields": {
        "Error 4xx": [
          {
            "group": "Error 4xx",
            "optional": false,
            "field": "NoAccessRight",
            "description": "<p>Only authenticated Admins can access the data.</p>"
          },
          {
            "group": "Error 4xx",
            "optional": false,
            "field": "UserNameTooShort",
            "description": "<p>Minimum of 5 characters required.</p>"
          }
        ]
      },
      "examples": [
        {
          "title": "Response (example):",
          "content": "HTTP/1.1 400 Bad Request\n{\n  \"error\": \"UserNameTooShort\"\n}",
          "type": "json"
        }
      ]
    }
  },
  {
    "type": "post",
    "url": "/my_work",
    "title": "MyWork",
    "version": "0.3.0",
    "name": "PostMyWork",
    "group": "Getter",
    "permission": [
      {
        "name": "none"
      }
    ],
    "description": "<p>我发布的菜谱</p>",
    "parameter": {
      "fields": {
        "Parameter": [
          {
            "group": "Parameter",
            "type": "String",
            "optional": false,
            "field": "id",
            "description": "<p>用户id.</p>"
          },
          {
            "group": "Parameter",
            "type": "Number",
            "optional": false,
            "field": "skip",
            "description": "<p>跳过指定数量.</p>"
          },
          {
            "group": "Parameter",
            "type": "Number",
            "optional": false,
            "field": "limit",
            "description": "<p>读取的记录条数.</p>"
          }
        ]
      }
    },
    "success": {
      "fields": {
        "Success 200": [
          {
            "group": "Success 200",
            "type": "Number",
            "optional": false,
            "field": "id",
            "description": "<p>The new Users-ID.</p>"
          }
        ]
      }
    },
    "filename": "example/example.js",
    "groupTitle": "Getter",
    "sampleRequest": [
      {
        "url": "https://devonhello.com/chihu_v3/my_work"
      }
    ],
    "error": {
      "fields": {
        "Error 4xx": [
          {
            "group": "Error 4xx",
            "optional": false,
            "field": "NoAccessRight",
            "description": "<p>Only authenticated Admins can access the data.</p>"
          },
          {
            "group": "Error 4xx",
            "optional": false,
            "field": "UserNameTooShort",
            "description": "<p>Minimum of 5 characters required.</p>"
          }
        ]
      },
      "examples": [
        {
          "title": "Response (example):",
          "content": "HTTP/1.1 400 Bad Request\n{\n  \"error\": \"UserNameTooShort\"\n}",
          "type": "json"
        }
      ]
    }
  },
  {
    "type": "post",
    "url": "/notification",
    "title": "Notification",
    "version": "0.3.0",
    "name": "PostNotification",
    "group": "Getter",
    "permission": [
      {
        "name": "none"
      }
    ],
    "description": "<p>系统通知</p>",
    "parameter": {
      "fields": {
        "Parameter": [
          {
            "group": "Parameter",
            "type": "String",
            "optional": false,
            "field": "id",
            "description": "<p>用户id.</p>"
          },
          {
            "group": "Parameter",
            "type": "Number",
            "optional": false,
            "field": "skip",
            "description": "<p>跳过指定数量.</p>"
          },
          {
            "group": "Parameter",
            "type": "Number",
            "optional": false,
            "field": "limit",
            "description": "<p>读取的记录条数.</p>"
          }
        ]
      }
    },
    "success": {
      "fields": {
        "Success 200": [
          {
            "group": "Success 200",
            "type": "Number",
            "optional": false,
            "field": "id",
            "description": "<p>The new Users-ID.</p>"
          }
        ]
      }
    },
    "filename": "example/example.js",
    "groupTitle": "Getter",
    "sampleRequest": [
      {
        "url": "https://devonhello.com/chihu_v3/notification"
      }
    ],
    "error": {
      "fields": {
        "Error 4xx": [
          {
            "group": "Error 4xx",
            "optional": false,
            "field": "NoAccessRight",
            "description": "<p>Only authenticated Admins can access the data.</p>"
          },
          {
            "group": "Error 4xx",
            "optional": false,
            "field": "UserNameTooShort",
            "description": "<p>Minimum of 5 characters required.</p>"
          }
        ]
      },
      "examples": [
        {
          "title": "Response (example):",
          "content": "HTTP/1.1 400 Bad Request\n{\n  \"error\": \"UserNameTooShort\"\n}",
          "type": "json"
        }
      ]
    }
  },
  {
    "type": "post",
    "url": "/question",
    "title": "Question",
    "version": "0.3.0",
    "name": "PostQuestion",
    "group": "Getter",
    "permission": [
      {
        "name": "none"
      }
    ],
    "description": "<p>问题的详细内容</p>",
    "parameter": {
      "fields": {
        "Parameter": [
          {
            "group": "Parameter",
            "type": "String",
            "optional": false,
            "field": "id",
            "description": "<p>问题的id.</p>"
          }
        ]
      }
    },
    "success": {
      "fields": {
        "Success 200": [
          {
            "group": "Success 200",
            "type": "Number",
            "optional": false,
            "field": "id",
            "description": "<p>The new Users-ID.</p>"
          }
        ]
      }
    },
    "filename": "example/example.js",
    "groupTitle": "Getter",
    "sampleRequest": [
      {
        "url": "https://devonhello.com/chihu_v3/question"
      }
    ],
    "error": {
      "fields": {
        "Error 4xx": [
          {
            "group": "Error 4xx",
            "optional": false,
            "field": "NoAccessRight",
            "description": "<p>Only authenticated Admins can access the data.</p>"
          },
          {
            "group": "Error 4xx",
            "optional": false,
            "field": "UserNameTooShort",
            "description": "<p>Minimum of 5 characters required.</p>"
          }
        ]
      },
      "examples": [
        {
          "title": "Response (example):",
          "content": "HTTP/1.1 400 Bad Request\n{\n  \"error\": \"UserNameTooShort\"\n}",
          "type": "json"
        }
      ]
    }
  },
  {
    "type": "post",
    "url": "/question_list",
    "title": "QuestionList",
    "version": "0.3.0",
    "name": "PostQuestionList",
    "group": "Getter",
    "permission": [
      {
        "name": "none"
      }
    ],
    "description": "<p>问题的详细内容</p>",
    "parameter": {
      "fields": {
        "Parameter": [
          {
            "group": "Parameter",
            "type": "Number",
            "optional": false,
            "field": "skip",
            "description": "<p>跳过指定数量.</p>"
          },
          {
            "group": "Parameter",
            "type": "Number",
            "optional": false,
            "field": "limit",
            "description": "<p>读取的记录条数.</p>"
          }
        ]
      }
    },
    "success": {
      "fields": {
        "Success 200": [
          {
            "group": "Success 200",
            "type": "Number",
            "optional": false,
            "field": "id",
            "description": "<p>The new Users-ID.</p>"
          }
        ]
      }
    },
    "filename": "example/example.js",
    "groupTitle": "Getter",
    "sampleRequest": [
      {
        "url": "https://devonhello.com/chihu_v3/question_list"
      }
    ],
    "error": {
      "fields": {
        "Error 4xx": [
          {
            "group": "Error 4xx",
            "optional": false,
            "field": "NoAccessRight",
            "description": "<p>Only authenticated Admins can access the data.</p>"
          },
          {
            "group": "Error 4xx",
            "optional": false,
            "field": "UserNameTooShort",
            "description": "<p>Minimum of 5 characters required.</p>"
          }
        ]
      },
      "examples": [
        {
          "title": "Response (example):",
          "content": "HTTP/1.1 400 Bad Request\n{\n  \"error\": \"UserNameTooShort\"\n}",
          "type": "json"
        }
      ]
    }
  },
  {
    "type": "post",
    "url": "/reply",
    "title": "Reply",
    "version": "0.3.0",
    "name": "PostReply",
    "group": "Getter",
    "permission": [
      {
        "name": "none"
      }
    ],
    "description": "<p>回复我的</p>",
    "parameter": {
      "fields": {
        "Parameter": [
          {
            "group": "Parameter",
            "type": "String",
            "optional": false,
            "field": "id",
            "description": "<p>用户id.</p>"
          },
          {
            "group": "Parameter",
            "type": "Number",
            "optional": false,
            "field": "skip",
            "description": "<p>跳过指定数量.</p>"
          },
          {
            "group": "Parameter",
            "type": "Number",
            "optional": false,
            "field": "limit",
            "description": "<p>读取的记录条数.</p>"
          }
        ]
      }
    },
    "success": {
      "fields": {
        "Success 200": [
          {
            "group": "Success 200",
            "type": "Number",
            "optional": false,
            "field": "id",
            "description": "<p>The new Users-ID.</p>"
          }
        ]
      }
    },
    "filename": "example/example.js",
    "groupTitle": "Getter",
    "sampleRequest": [
      {
        "url": "https://devonhello.com/chihu_v3/reply"
      }
    ],
    "error": {
      "fields": {
        "Error 4xx": [
          {
            "group": "Error 4xx",
            "optional": false,
            "field": "NoAccessRight",
            "description": "<p>Only authenticated Admins can access the data.</p>"
          },
          {
            "group": "Error 4xx",
            "optional": false,
            "field": "UserNameTooShort",
            "description": "<p>Minimum of 5 characters required.</p>"
          }
        ]
      },
      "examples": [
        {
          "title": "Response (example):",
          "content": "HTTP/1.1 400 Bad Request\n{\n  \"error\": \"UserNameTooShort\"\n}",
          "type": "json"
        }
      ]
    }
  },
  {
    "type": "post",
    "url": "/share",
    "title": "Share",
    "version": "0.3.0",
    "name": "PostShare",
    "group": "Getter",
    "permission": [
      {
        "name": "none"
      }
    ],
    "description": "<p>分享（获取分享的详细内容）</p>",
    "parameter": {
      "fields": {
        "Parameter": [
          {
            "group": "Parameter",
            "type": "String",
            "optional": false,
            "field": "id",
            "description": "<p>分享的id.</p>"
          }
        ]
      }
    },
    "success": {
      "fields": {
        "Success 200": [
          {
            "group": "Success 200",
            "type": "Number",
            "optional": false,
            "field": "id",
            "description": "<p>The new Users-ID.</p>"
          }
        ]
      }
    },
    "filename": "example/example.js",
    "groupTitle": "Getter",
    "sampleRequest": [
      {
        "url": "https://devonhello.com/chihu_v3/share"
      }
    ],
    "error": {
      "fields": {
        "Error 4xx": [
          {
            "group": "Error 4xx",
            "optional": false,
            "field": "NoAccessRight",
            "description": "<p>Only authenticated Admins can access the data.</p>"
          },
          {
            "group": "Error 4xx",
            "optional": false,
            "field": "UserNameTooShort",
            "description": "<p>Minimum of 5 characters required.</p>"
          }
        ]
      },
      "examples": [
        {
          "title": "Response (example):",
          "content": "HTTP/1.1 400 Bad Request\n{\n  \"error\": \"UserNameTooShort\"\n}",
          "type": "json"
        }
      ]
    }
  },
  {
    "type": "post",
    "url": "/share_list",
    "title": "ShareList",
    "version": "0.3.0",
    "name": "PostShareList",
    "group": "Getter",
    "permission": [
      {
        "name": "none"
      }
    ],
    "description": "<p>分享（获取分享的详细内容）</p>",
    "parameter": {
      "fields": {
        "Parameter": [
          {
            "group": "Parameter",
            "type": "Number",
            "optional": false,
            "field": "skip",
            "description": "<p>跳过指定数量.</p>"
          },
          {
            "group": "Parameter",
            "type": "Number",
            "optional": false,
            "field": "limit",
            "description": "<p>读取的记录条数.</p>"
          }
        ]
      }
    },
    "success": {
      "fields": {
        "Success 200": [
          {
            "group": "Success 200",
            "type": "Number",
            "optional": false,
            "field": "id",
            "description": "<p>The new Users-ID.</p>"
          }
        ]
      }
    },
    "filename": "example/example.js",
    "groupTitle": "Getter",
    "sampleRequest": [
      {
        "url": "https://devonhello.com/chihu_v3/share_list"
      }
    ],
    "error": {
      "fields": {
        "Error 4xx": [
          {
            "group": "Error 4xx",
            "optional": false,
            "field": "NoAccessRight",
            "description": "<p>Only authenticated Admins can access the data.</p>"
          },
          {
            "group": "Error 4xx",
            "optional": false,
            "field": "UserNameTooShort",
            "description": "<p>Minimum of 5 characters required.</p>"
          }
        ]
      },
      "examples": [
        {
          "title": "Response (example):",
          "content": "HTTP/1.1 400 Bad Request\n{\n  \"error\": \"UserNameTooShort\"\n}",
          "type": "json"
        }
      ]
    }
  },
  {
    "type": "post",
    "url": "/thank",
    "title": "Thank",
    "version": "0.3.0",
    "name": "PostThank",
    "group": "Getter",
    "permission": [
      {
        "name": "none"
      }
    ],
    "description": "<p>感谢我的</p>",
    "parameter": {
      "fields": {
        "Parameter": [
          {
            "group": "Parameter",
            "type": "String",
            "optional": false,
            "field": "id",
            "description": "<p>用户id.</p>"
          },
          {
            "group": "Parameter",
            "type": "Number",
            "optional": false,
            "field": "skip",
            "description": "<p>跳过指定数量.</p>"
          },
          {
            "group": "Parameter",
            "type": "Number",
            "optional": false,
            "field": "limit",
            "description": "<p>读取的记录条数.</p>"
          }
        ]
      }
    },
    "success": {
      "fields": {
        "Success 200": [
          {
            "group": "Success 200",
            "type": "Number",
            "optional": false,
            "field": "id",
            "description": "<p>The new Users-ID.</p>"
          }
        ]
      }
    },
    "filename": "example/example.js",
    "groupTitle": "Getter",
    "sampleRequest": [
      {
        "url": "https://devonhello.com/chihu_v3/thank"
      }
    ],
    "error": {
      "fields": {
        "Error 4xx": [
          {
            "group": "Error 4xx",
            "optional": false,
            "field": "NoAccessRight",
            "description": "<p>Only authenticated Admins can access the data.</p>"
          },
          {
            "group": "Error 4xx",
            "optional": false,
            "field": "UserNameTooShort",
            "description": "<p>Minimum of 5 characters required.</p>"
          }
        ]
      },
      "examples": [
        {
          "title": "Response (example):",
          "content": "HTTP/1.1 400 Bad Request\n{\n  \"error\": \"UserNameTooShort\"\n}",
          "type": "json"
        }
      ]
    }
  },
  {
    "type": "post",
    "url": "/user",
    "title": "User",
    "version": "0.3.0",
    "name": "PostUser",
    "group": "Getter",
    "permission": [
      {
        "name": "none"
      }
    ],
    "description": "<p>用户的详细资料</p>",
    "parameter": {
      "fields": {
        "Parameter": [
          {
            "group": "Parameter",
            "type": "String",
            "optional": false,
            "field": "id",
            "description": "<p>用户的id.</p>"
          }
        ]
      }
    },
    "success": {
      "fields": {
        "Success 200": [
          {
            "group": "Success 200",
            "type": "Number",
            "optional": false,
            "field": "id",
            "description": "<p>The new Users-ID.</p>"
          }
        ]
      }
    },
    "filename": "example/example.js",
    "groupTitle": "Getter",
    "sampleRequest": [
      {
        "url": "https://devonhello.com/chihu_v3/user"
      }
    ],
    "error": {
      "fields": {
        "Error 4xx": [
          {
            "group": "Error 4xx",
            "optional": false,
            "field": "NoAccessRight",
            "description": "<p>Only authenticated Admins can access the data.</p>"
          },
          {
            "group": "Error 4xx",
            "optional": false,
            "field": "UserNameTooShort",
            "description": "<p>Minimum of 5 characters required.</p>"
          }
        ]
      },
      "examples": [
        {
          "title": "Response (example):",
          "content": "HTTP/1.1 400 Bad Request\n{\n  \"error\": \"UserNameTooShort\"\n}",
          "type": "json"
        }
      ]
    }
  },
  {
    "type": "post",
    "url": "/version",
    "title": "Version",
    "version": "0.3.0",
    "name": "PostVersion",
    "group": "Getter",
    "permission": [
      {
        "name": "none"
      }
    ],
    "description": "<p>获取APP最新版本号</p>",
    "success": {
      "fields": {
        "Success 200": [
          {
            "group": "Success 200",
            "type": "String",
            "optional": false,
            "field": "version",
            "description": "<p>最新的版本号.</p>"
          },
          {
            "group": "Success 200",
            "type": "String",
            "optional": false,
            "field": "url",
            "description": "<p>最新版本的下载地址.</p>"
          }
        ]
      }
    },
    "filename": "example/example.js",
    "groupTitle": "Getter",
    "sampleRequest": [
      {
        "url": "https://devonhello.com/chihu_v3/version"
      }
    ],
    "error": {
      "fields": {
        "Error 4xx": [
          {
            "group": "Error 4xx",
            "optional": false,
            "field": "NoAccessRight",
            "description": "<p>Only authenticated Admins can access the data.</p>"
          },
          {
            "group": "Error 4xx",
            "optional": false,
            "field": "UserNameTooShort",
            "description": "<p>Minimum of 5 characters required.</p>"
          }
        ]
      },
      "examples": [
        {
          "title": "Response (example):",
          "content": "HTTP/1.1 400 Bad Request\n{\n  \"error\": \"UserNameTooShort\"\n}",
          "type": "json"
        }
      ]
    }
  },
  {
    "type": "post",
    "url": "/work",
    "title": "Work",
    "version": "0.3.0",
    "name": "PostWork",
    "group": "Getter",
    "permission": [
      {
        "name": "none"
      }
    ],
    "description": "<p>菜谱（获取菜谱的详细内容）</p>",
    "parameter": {
      "fields": {
        "Parameter": [
          {
            "group": "Parameter",
            "type": "String",
            "optional": false,
            "field": "id",
            "description": "<p>菜谱的id.</p>"
          }
        ]
      }
    },
    "success": {
      "fields": {
        "Success 200": [
          {
            "group": "Success 200",
            "type": "Number",
            "optional": false,
            "field": "id",
            "description": "<p>The new Users-ID.</p>"
          }
        ]
      }
    },
    "filename": "example/example.js",
    "groupTitle": "Getter",
    "sampleRequest": [
      {
        "url": "https://devonhello.com/chihu_v3/work"
      }
    ],
    "error": {
      "fields": {
        "Error 4xx": [
          {
            "group": "Error 4xx",
            "optional": false,
            "field": "NoAccessRight",
            "description": "<p>Only authenticated Admins can access the data.</p>"
          },
          {
            "group": "Error 4xx",
            "optional": false,
            "field": "UserNameTooShort",
            "description": "<p>Minimum of 5 characters required.</p>"
          }
        ]
      },
      "examples": [
        {
          "title": "Response (example):",
          "content": "HTTP/1.1 400 Bad Request\n{\n  \"error\": \"UserNameTooShort\"\n}",
          "type": "json"
        }
      ]
    }
  },
  {
    "type": "post",
    "url": "/work_list",
    "title": "WorkList",
    "version": "0.3.0",
    "name": "PostWorkList",
    "group": "Getter",
    "permission": [
      {
        "name": "none"
      }
    ],
    "description": "<p>菜谱列表</p>",
    "parameter": {
      "fields": {
        "Parameter": [
          {
            "group": "Parameter",
            "type": "Number",
            "optional": false,
            "field": "skip",
            "description": "<p>跳过指定数量.</p>"
          },
          {
            "group": "Parameter",
            "type": "Number",
            "optional": false,
            "field": "limit",
            "description": "<p>读取的记录条数.</p>"
          }
        ]
      }
    },
    "success": {
      "fields": {
        "Success 200": [
          {
            "group": "Success 200",
            "type": "Number",
            "optional": false,
            "field": "id",
            "description": "<p>The new Users-ID.</p>"
          }
        ]
      }
    },
    "filename": "example/example.js",
    "groupTitle": "Getter",
    "sampleRequest": [
      {
        "url": "https://devonhello.com/chihu_v3/work_list"
      }
    ],
    "error": {
      "fields": {
        "Error 4xx": [
          {
            "group": "Error 4xx",
            "optional": false,
            "field": "NoAccessRight",
            "description": "<p>Only authenticated Admins can access the data.</p>"
          },
          {
            "group": "Error 4xx",
            "optional": false,
            "field": "UserNameTooShort",
            "description": "<p>Minimum of 5 characters required.</p>"
          }
        ]
      },
      "examples": [
        {
          "title": "Response (example):",
          "content": "HTTP/1.1 400 Bad Request\n{\n  \"error\": \"UserNameTooShort\"\n}",
          "type": "json"
        }
      ]
    }
  },
  {
    "type": "post",
    "url": "/send_article",
    "title": "SendArticle",
    "version": "0.3.0",
    "name": "PostSendArticle",
    "group": "Setter",
    "permission": [
      {
        "name": "none"
      }
    ],
    "description": "<p>发布文章</p>",
    "parameter": {
      "fields": {
        "Parameter": [
          {
            "group": "Parameter",
            "type": "String",
            "optional": false,
            "field": "title",
            "description": "<p>文章标题</p>"
          },
          {
            "group": "Parameter",
            "type": "String",
            "optional": false,
            "field": "uid",
            "description": "<p>作者id</p>"
          },
          {
            "group": "Parameter",
            "type": "String",
            "optional": false,
            "field": "uname",
            "description": "<p>作者名称</p>"
          },
          {
            "group": "Parameter",
            "type": "String",
            "optional": false,
            "field": "uimgsrc",
            "description": "<p>作者头像</p>"
          },
          {
            "group": "Parameter",
            "type": "String",
            "optional": false,
            "field": "text",
            "description": "<p>文章内容</p>"
          },
          {
            "group": "Parameter",
            "type": "String",
            "optional": false,
            "field": "questionId",
            "description": "<p>问题的id（可选，questionId有值title为问题的标题）</p>"
          }
        ]
      }
    },
    "success": {
      "fields": {
        "Success 200": [
          {
            "group": "Success 200",
            "type": "String",
            "optional": false,
            "field": "_id",
            "description": "<p>文章id</p>"
          },
          {
            "group": "Success 200",
            "type": "String",
            "optional": false,
            "field": "title",
            "description": "<p>文章标题</p>"
          },
          {
            "group": "Success 200",
            "type": "String",
            "optional": false,
            "field": "uid",
            "description": "<p>作者id</p>"
          },
          {
            "group": "Success 200",
            "type": "String",
            "optional": false,
            "field": "uname",
            "description": "<p>作者名称</p>"
          },
          {
            "group": "Success 200",
            "type": "String",
            "optional": false,
            "field": "uimgsrc",
            "description": "<p>作者头像</p>"
          },
          {
            "group": "Success 200",
            "type": "String",
            "optional": false,
            "field": "text",
            "description": "<p>文章内容</p>"
          },
          {
            "group": "Success 200",
            "type": "String",
            "optional": false,
            "field": "questionId",
            "description": "<p>问题的id（可无）</p>"
          },
          {
            "group": "Success 200",
            "type": "String",
            "optional": false,
            "field": "time",
            "description": "<p>发布时间</p>"
          },
          {
            "group": "Success 200",
            "type": "String",
            "optional": false,
            "field": "report",
            "description": "<p>举报的次数</p>"
          },
          {
            "group": "Success 200",
            "type": "String",
            "optional": false,
            "field": "comment",
            "description": "<p>评论数</p>"
          },
          {
            "group": "Success 200",
            "type": "String",
            "optional": false,
            "field": "collect",
            "description": "<p>收藏数</p>"
          },
          {
            "group": "Success 200",
            "type": "String",
            "optional": false,
            "field": "think",
            "description": "<p>感谢数</p>"
          },
          {
            "group": "Success 200",
            "type": "String",
            "optional": false,
            "field": "pass",
            "description": "<p>是否通过审核（0不通过、1通过）</p>"
          }
        ]
      }
    },
    "filename": "example/example.js",
    "groupTitle": "Setter",
    "sampleRequest": [
      {
        "url": "https://devonhello.com/chihu_v3/send_article"
      }
    ],
    "error": {
      "fields": {
        "Error 4xx": [
          {
            "group": "Error 4xx",
            "optional": false,
            "field": "NoAccessRight",
            "description": "<p>Only authenticated Admins can access the data.</p>"
          },
          {
            "group": "Error 4xx",
            "optional": false,
            "field": "UserNameTooShort",
            "description": "<p>Minimum of 5 characters required.</p>"
          }
        ]
      },
      "examples": [
        {
          "title": "Response (example):",
          "content": "HTTP/1.1 400 Bad Request\n{\n  \"error\": \"UserNameTooShort\"\n}",
          "type": "json"
        }
      ]
    }
  },
  {
    "type": "post",
    "url": "/send_work",
    "title": "SendWork",
    "version": "0.3.0",
    "name": "PostSendWork",
    "group": "Setter",
    "permission": [
      {
        "name": "none"
      }
    ],
    "description": "<p>发布菜谱</p>",
    "parameter": {
      "fields": {
        "Parameter": [
          {
            "group": "Parameter",
            "type": "String",
            "optional": false,
            "field": "title",
            "description": "<p>菜谱名称</p>"
          },
          {
            "group": "Parameter",
            "type": "String",
            "optional": false,
            "field": "ban",
            "description": "<p>成品图地址</p>"
          },
          {
            "group": "Parameter",
            "type": "String",
            "optional": false,
            "field": "uid",
            "description": "<p>作者id</p>"
          },
          {
            "group": "Parameter",
            "type": "String",
            "optional": false,
            "field": "uname",
            "description": "<p>作者名称</p>"
          },
          {
            "group": "Parameter",
            "type": "String",
            "optional": false,
            "field": "uimgsrc",
            "description": "<p>作者头像</p>"
          },
          {
            "group": "Parameter",
            "type": "String",
            "optional": false,
            "field": "dec",
            "description": "<p>菜谱介绍（可选）</p>"
          },
          {
            "group": "Parameter",
            "type": "String[]",
            "optional": false,
            "field": "iclassId",
            "description": "<p>分类id</p>"
          },
          {
            "group": "Parameter",
            "type": "String",
            "optional": false,
            "field": "tip",
            "description": "<p>提示（可选</p>"
          },
          {
            "group": "Parameter",
            "type": "Object[]",
            "optional": false,
            "field": "food",
            "description": "<p>食材 （{ len：‘食材数量’，name：‘食材名称’ }）</p>"
          },
          {
            "group": "Parameter",
            "type": "Object[]",
            "optional": false,
            "field": "step",
            "description": "<p>步骤 （{ t：‘步骤说明’，src：‘步骤图地址’，w：‘图的宽度’，h：‘图的高度’ }）</p>"
          }
        ]
      }
    },
    "success": {
      "fields": {
        "Success 200": [
          {
            "group": "Success 200",
            "type": "String",
            "optional": false,
            "field": "_id",
            "description": "<p>文章id</p>"
          },
          {
            "group": "Success 200",
            "type": "String",
            "optional": false,
            "field": "title",
            "description": "<p>文章标题</p>"
          },
          {
            "group": "Success 200",
            "type": "String",
            "optional": false,
            "field": "uid",
            "description": "<p>作者id</p>"
          },
          {
            "group": "Success 200",
            "type": "String",
            "optional": false,
            "field": "uname",
            "description": "<p>作者名称</p>"
          },
          {
            "group": "Success 200",
            "type": "String",
            "optional": false,
            "field": "uimgsrc",
            "description": "<p>作者头像</p>"
          },
          {
            "group": "Success 200",
            "type": "String",
            "optional": false,
            "field": "text",
            "description": "<p>文章内容</p>"
          },
          {
            "group": "Success 200",
            "type": "String",
            "optional": false,
            "field": "questionId",
            "description": "<p>问题的id（可无）</p>"
          },
          {
            "group": "Success 200",
            "type": "String",
            "optional": false,
            "field": "time",
            "description": "<p>发布时间</p>"
          },
          {
            "group": "Success 200",
            "type": "String",
            "optional": false,
            "field": "report",
            "description": "<p>举报的次数</p>"
          },
          {
            "group": "Success 200",
            "type": "String",
            "optional": false,
            "field": "comment",
            "description": "<p>评论数</p>"
          },
          {
            "group": "Success 200",
            "type": "String",
            "optional": false,
            "field": "collect",
            "description": "<p>收藏数</p>"
          },
          {
            "group": "Success 200",
            "type": "String",
            "optional": false,
            "field": "think",
            "description": "<p>感谢数</p>"
          },
          {
            "group": "Success 200",
            "type": "String",
            "optional": false,
            "field": "pass",
            "description": "<p>是否通过审核（0不通过、1通过）</p>"
          }
        ]
      }
    },
    "filename": "example/example.js",
    "groupTitle": "Setter",
    "sampleRequest": [
      {
        "url": "https://devonhello.com/chihu_v3/send_work"
      }
    ],
    "error": {
      "fields": {
        "Error 4xx": [
          {
            "group": "Error 4xx",
            "optional": false,
            "field": "NoAccessRight",
            "description": "<p>Only authenticated Admins can access the data.</p>"
          },
          {
            "group": "Error 4xx",
            "optional": false,
            "field": "UserNameTooShort",
            "description": "<p>Minimum of 5 characters required.</p>"
          }
        ]
      },
      "examples": [
        {
          "title": "Response (example):",
          "content": "HTTP/1.1 400 Bad Request\n{\n  \"error\": \"UserNameTooShort\"\n}",
          "type": "json"
        }
      ]
    }
  }
]
